ipm/__init__.py
ipm/__main__.py
ipm/__version__.py
ipm/common.py
ipm/manage.py
ci_ipm-0.2.0.dist-info/LICENSE
ci_ipm-0.2.0.dist-info/METADATA
ci_ipm-0.2.0.dist-info/WHEEL
ci_ipm-0.2.0.dist-info/entry_points.txt
ci_ipm-0.2.0.dist-info/top_level.txt
ci_ipm-0.2.0.dist-info/RECORD
