Metadata-Version: 2.1
Name: ci-ipm
Version: 0.2.0
Summary: Open-source IPs Package Manager.
Author: Efabless Corporation
Author-email: marwan.abbas@efabless.com
Classifier: License :: OSI Approved :: Apache Software License
Classifier: Programming Language :: Python :: 3
Classifier: Intended Audience :: Developers
Classifier: Operating System :: POSIX :: Linux
Classifier: Operating System :: MacOS :: MacOS X
Requires-Python: >3.6
License-File: LICENSE
Requires-Dist: requirements.txt
